pygenpdf/__init__.py
pygenpdf/genpdf.py
pygenpdf-0.1.12.dist-info/licenses/LICENSE
pygenpdf-0.1.12.dist-info/METADATA
pygenpdf-0.1.12.dist-info/WHEEL
pygenpdf-0.1.12.dist-info/top_level.txt
pygenpdf-0.1.12.dist-info/RECORD
