Metadata-Version: 2.4
Name: pygenpdf
Version: 0.1.12
Summary: access pygenpdf_json in a pythonic way (the pygenpdf-json library is a PDF generator)
Author-email: Numael Garay <mantrixsoft@gmail.com>
Project-URL: Homepage, https://gitlab.com/numaelis/pygenpdf
Classifier: Programming Language :: Python :: 3
Classifier: License :: OSI Approved :: GNU General Public License v3 (GPLv3)
Classifier: Topic :: Software Development :: Libraries
Classifier: Topic :: Software Development :: Libraries :: Python Modules
Requires-Python: >=3.8
License-File: LICENSE
Requires-Dist: pygenpdf_json
Dynamic: license-file
